pygemini/__init__.py
pygemini/__version__.py
pygemini/core.py
pygemini-1.0.2.dist-info/METADATA
pygemini-1.0.2.dist-info/WHEEL
pygemini-1.0.2.dist-info/top_level.txt
pygemini-1.0.2.dist-info/RECORD
